Minecraft_Pi/Exception.py
Minecraft_Pi/InfoProcessing.py
Minecraft_Pi/RemoteServer.py
Minecraft_Pi/ServerType.py
Minecraft_Pi/__init__.py
Minecraft_Pi-1.1.dist-info/LICENSE
Minecraft_Pi-1.1.dist-info/METADATA
Minecraft_Pi-1.1.dist-info/WHEEL
Minecraft_Pi-1.1.dist-info/top_level.txt
Minecraft_Pi-1.1.dist-info/RECORD
