Metadata-Version: 2.1
Name: Minecraft-Pi
Version: 1.1
Summary: 用于远程获取玩家信息的API
Home-page: UNKNOWN
Author: Minecraft Player Information Team
Author-email: UNKNOWN
License: MIT License
Platform: UNKNOWN
